{
    "playerStats": [
        {
            "stats": {
                "mins_played": [
                    45,
                    1
                ],
                "goals": [
                    0,
                    0
                ],
                "goal_assist": [
                    0,
                    0
                ],
                "offtarget_att_assist": [
                    0,
                    0
                ],
                "pen_area_entries": [
                    0,
                    0
                ],
                "penalty_won": [
                    0,
                    0
                ],
                "penalty_save": [
                    0,
                    0
                ],
                "saves": [
                    0,
                    0
                ],
                "effective_clearance": [
                    0,
                    0
                ],
                "penalty_failed": [
                    0,
                    0
                ],
                "own_goals": [
                    0,
                    0
                ],
                "goals_conceded": [
                    0,
                    0
                ],
                "yellow_card": [
                    0,
                    0
                ],
                "second_yellow_card": [
                    0,
                    0
                ],
                "red_card": [
                    0,
                    0
                ],
                "total_scoring_att": [
                    0,
                    0
                ],
                "won_contest": [
                    0,
                    0
                ],
                "ball_recovery": [
                    2,
                    0
                ],
                "poss_lost_all": [
                    7,
                    0
                ],
                "penalty_conceded": [
                    0,
                    0
                ],
                "marca_points": [
                    -1,
                    1
                ]
            },
            "weekNumber": 1,
            "totalPoints": 2,
            "isInIdealFormation": false
        },
        {
            "stats": {
                "mins_played": [
                    65,
                    2
                ],
                "goals": [
                    1,
                    4
                ],
                "goal_assist": [
                    0,
                    0
                ],
                "offtarget_att_assist": [
                    0,
                    0
                ],
                "pen_area_entries": [
                    0,
                    0
                ],
                "penalty_won": [
                    0,
                    0
                ],
                "penalty_save": [
                    0,
                    0
                ],
                "saves": [
                    0,
                    0
                ],
                "effective_clearance": [
                    2,
                    0
                ],
                "penalty_failed": [
                    0,
                    0
                ],
                "own_goals": [
                    0,
                    0
                ],
                "goals_conceded": [
                    0,
                    1
                ],
                "yellow_card": [
                    0,
                    0
                ],
                "second_yellow_card": [
                    0,
                    0
                ],
                "red_card": [
                    0,
                    0
                ],
                "total_scoring_att": [
                    1,
                    0
                ],
                "won_contest": [
                    1,
                    0
                ],
                "ball_recovery": [
                    2,
                    0
                ],
                "poss_lost_all": [
                    11,
                    0
                ],
                "penalty_conceded": [
                    0,
                    0
                ],
                "marca_points": [
                    -1,
                    2
                ]
            },
            "weekNumber": 2,
            "totalPoints": 9,
            "isInIdealFormation": false
        },
        {
            "stats": {
                "mins_played": [
                    66,
                    2
                ],
                "goals": [
                    1,
                    4
                ],
                "goal_assist": [
                    0,
                    0
                ],
                "offtarget_att_assist": [
                    0,
                    0
                ],
                "pen_area_entries": [
                    0,
                    0
                ],
                "penalty_won": [
                    0,
                    0
                ],
                "penalty_save": [
                    0,
                    0
                ],
                "saves": [
                    0,
                    0
                ],
                "effective_clearance": [
                    0,
                    0
                ],
                "penalty_failed": [
                    0,
                    0
                ],
                "own_goals": [
                    0,
                    0
                ],
                "goals_conceded": [
                    2,
                    -1
                ],
                "yellow_card": [
                    0,
                    0
                ],
                "second_yellow_card": [
                    0,
                    0
                ],
                "red_card": [
                    0,
                    0
                ],
                "total_scoring_att": [
                    2,
                    1
                ],
                "won_contest": [
                    0,
                    0
                ],
                "ball_recovery": [
                    2,
                    0
                ],
                "poss_lost_all": [
                    13,
                    -1
                ],
                "penalty_conceded": [
                    0,
                    0
                ],
                "marca_points": [
                    -1,
                    2
                ]
            },
            "weekNumber": 3,
            "totalPoints": 7,
            "isInIdealFormation": false
        },
        {
            "stats": {
                "mins_played": [
                    90,
                    2
                ],
                "goals": [
                    0,
                    0
                ],
                "goal_assist": [
                    0,
                    0
                ],
                "offtarget_att_assist": [
                    0,
                    0
                ],
                "pen_area_entries": [
                    0,
                    0
                ],
                "penalty_won": [
                    0,
                    0
                ],
                "penalty_save": [
                    0,
                    0
                ],
                "saves": [
                    0,
                    0
                ],
                "effective_clearance": [
                    1,
                    0
                ],
                "penalty_failed": [
                    0,
                    0
                ],
                "own_goals": [
                    0,
                    0
                ],
                "goals_conceded": [
                    0,
                    1
                ],
                "yellow_card": [
                    0,
                    0
                ],
                "second_yellow_card": [
                    0,
                    0
                ],
                "red_card": [
                    0,
                    0
                ],
                "total_scoring_att": [
                    0,
                    0
                ],
                "won_contest": [
                    1,
                    0
                ],
                "ball_recovery": [
                    4,
                    0
                ],
                "poss_lost_all": [
                    8,
                    0
                ],
                "penalty_conceded": [
                    0,
                    0
                ],
                "marca_points": [
                    -1,
                    2
                ]
            },
            "weekNumber": 4,
            "totalPoints": 5,
            "isInIdealFormation": false
        },
        {
            "stats": {
                "mins_played": [
                    0,
                    0
                ],
                "goals": [
                    0,
                    0
                ],
                "goal_assist": [
                    0,
                    0
                ],
                "offtarget_att_assist": [
                    0,
                    0
                ],
                "pen_area_entries": [
                    0,
                    0
                ],
                "penalty_won": [
                    0,
                    0
                ],
                "penalty_save": [
                    0,
                    0
                ],
                "saves": [
                    0,
                    0
                ],
                "effective_clearance": [
                    0,
                    0
                ],
                "penalty_failed": [
                    0,
                    0
                ],
                "own_goals": [
                    0,
                    0
                ],
                "goals_conceded": [
                    0,
                    0
                ],
                "yellow_card": [
                    0,
                    0
                ],
                "second_yellow_card": [
                    0,
                    0
                ],
                "red_card": [
                    0,
                    0
                ],
                "total_scoring_att": [
                    0,
                    0
                ],
                "won_contest": [
                    0,
                    0
                ],
                "ball_recovery": [
                    0,
                    0
                ],
                "poss_lost_all": [
                    0,
                    0
                ],
                "penalty_conceded": [
                    0,
                    0
                ],
                "marca_points": [
                    -1,
                    0
                ]
            },
            "weekNumber": 4,
            "totalPoints": 0,
            "isInIdealFormation": false
        }
    ],
    "points": 23,
    "weekPoints": 5,
    "averagePoints": 4.6,
    "id": "1484",
    "team": {
        "badgeColor": "https://assets-fantasy.llt-services.com/teambadge/t174/color/t174_athletic-club.png",
        "badgeGray": "https://assets-fantasy.llt-services.com/teambadge/t174/gray/t174_athletic-club.png",
        "badgeWhite": "https://assets-fantasy.llt-services.com/teambadge/t174/white/t174_athletic-club.png",
        "name": "Athletic Club",
        "id": "3",
        "shortName": "ATH",
        "slug": "athletic-club",
        "dspId": 68,
        "store": ""
    },
    "name": "Gorka Guruzeta",
    "lastSeasonPoints": 112,
    "nickname": "Guruzeta",
    "slug": "guruzeta",
    "positionId": 4,
    "position": "Delantero",
    "marketValue": {
        "13/07/2023": 4000000,
        "14/07/2023": 3997192,
        "15/07/2023": 3994497,
        "16/07/2023": 3912800,
        "17/07/2023": 3879305,
        "18/07/2023": 3853494,
        "19/07/2023": 3810131,
        "20/07/2023": 3767942,
        "21/07/2023": 3736475,
        "22/07/2023": 3690832,
        "23/07/2023": 3653082,
        "24/07/2023": 3610434,
        "25/07/2023": 3557594,
        "26/07/2023": 3518333,
        "27/07/2023": 3491595,
        "28/07/2023": 3442633,
        "29/07/2023": 3401192,
        "30/07/2023": 3357924,
        "31/07/2023": 3328023,
        "01/08/2023": 3298836,
        "02/08/2023": 3270388,
        "03/08/2023": 3236489,
        "04/08/2023": 3194874,
        "05/08/2023": 3163065,
        "06/08/2023": 3123653,
        "07/08/2023": 3082192,
        "08/08/2023": 3045775,
        "09/08/2023": 3013520,
        "10/08/2023": 2985554,
        "11/08/2023": 2958906,
        "12/08/2023": 2939898,
        "13/08/2023": 2890182,
        "14/08/2023": 2827295,
        "15/08/2023": 2760232,
        "16/08/2023": 2692144,
        "17/08/2023": 2627767,
        "18/08/2023": 2579828,
        "19/08/2023": 2527775,
        "20/08/2023": 2477080,
        "21/08/2023": 2566706,
        "22/08/2023": 2705504,
        "23/08/2023": 2837429,
        "24/08/2023": 2966052,
        "25/08/2023": 3115612,
        "26/08/2023": 3252870,
        "27/08/2023": 3359860,
        "28/08/2023": 3436413,
        "29/08/2023": 3641911,
        "30/08/2023": 3885473,
        "31/08/2023": 4140340,
        "01/09/2023": 4401423,
        "02/09/2023": 4670806,
        "03/09/2023": 4903810,
        "04/09/2023": 5090745,
        "05/09/2023": 5320651,
        "06/09/2023": 5567592,
        "07/09/2023": 5773195,
        "08/09/2023": 6014102,
        "09/09/2023": 6236317,
        "10/09/2023": 6444095,
        "11/09/2023": 6643801,
        "12/09/2023": 6864667,
        "13/09/2023": 7067116,
        "14/09/2023": 7305893,
        "15/09/2023": 7512123
    },
    "playerStatus": "ok"
}